plugs_payments/__init__.py
plugs_payments/apps.py
plugs_payments/fields.py
plugs_payments/managers.py
plugs_payments/models.py
plugs_payments/settings.py
plugs_payments/signals.py
plugs_payments/views.py
plugs_payments/migrations/0001_initial.py
plugs_payments/migrations/0002_auto_20170109_1847.py
plugs_payments/migrations/0003_auto_20170109_1851.py
plugs_payments/migrations/0004_auto_20170109_2011.py
plugs_payments/migrations/0005_auto_20170118_1818.py
plugs_payments/migrations/__init__.py
plugs_payments/static/css/plugs_payments.css
plugs_payments/static/js/plugs_payments.js
plugs_payments/templates/plugs_payments/base.html
plugs_payments-0.2.0.dist-info/DESCRIPTION.rst
plugs_payments-0.2.0.dist-info/METADATA
plugs_payments-0.2.0.dist-info/RECORD
plugs_payments-0.2.0.dist-info/WHEEL
plugs_payments-0.2.0.dist-info/metadata.json
plugs_payments-0.2.0.dist-info/top_level.txt
