Metadata-Version: 2.0
Name: plugs-payments
Version: 0.2.0
Summary: Reusable Payments APP
Home-page: https://github.com/solocompt/plugs-payments
Author: Solo
Author-email: geral@solo.com.pt
License: MIT
Keywords: plugs-payments
Platform: UNKNOWN
Classifier: Development Status :: 3 - Alpha
Classifier: Framework :: Django :: 1.11
Classifier: Intended Audience :: Developers
Classifier: License :: OSI Approved :: MIT License
Classifier: Natural Language :: English
Classifier: Programming Language :: Python :: 3
Requires-Dist: plugs-core (>=0.1.6,<1.0.0)
